kimdb/__init__.py
kimdb/_parser.py
kimdb/imdb.py
kimdb/models/__init__.py
kimdb/models/base_company.py
kimdb/models/base_list.py
kimdb/models/base_name.py
kimdb/models/base_object.py
kimdb/models/base_title.py
kimdb/models/base_user.py
kimdb/models/imaged_title.py
kimdb/models/name.py
kimdb/models/title.py
kimdb/models/title_list.py
kimdb/models/urls.py
kimdb/models/user.py
kimdb/models/video.py
kimdb/models/enums/__init__.py
kimdb/models/enums/entry_type.py
kimdb-0.0.16.dist-info/LICENSE
kimdb-0.0.16.dist-info/METADATA
kimdb-0.0.16.dist-info/WHEEL
kimdb-0.0.16.dist-info/top_level.txt
kimdb-0.0.16.dist-info/RECORD
